{
    "version": 1,
    "camera": {
        "ang_degrees": -35,
        "vang_degrees": 0,
        "zoom": 0.45,
        "height": 8,
        "rotate_limit_degrees_min": -30,
        "rotate_limit_degrees_max": 0,
        "rotate_speed": 0.2
    },
	"map_tiles": 
	{
		"ceiling": 0,
		"width": 4,
		"height": 5,
		"floor": [
			63, 63, 63, 63,
			63, 63, 63, 63,
			64, 64, 64, 64,	
			64, 64, 64, 64,			
			64, 64, 64, 64
		],
		"mid": [
			74, 0, 0, 0,
			74, 0, 0, 0,
			74, 0, 0, 0,			
			74, 73, 294, 294,
			74, 74, 294, 294		
		],
		"top": [
			74, 0, 0, 0,
			121, 0, 0, 0,
			74, 0, 0, 0,			
			74, 73, 0, 0,
			74, 74, 294, 294
		]
	},			
    "limbs": [
        {
            "x": 20,
            "y": -25,
            "z": -8,
            "pitch": 0.0,
            "roll": 0.0,
            "yaw": 0.0,
            "focalx": 0.0,
            "focaly": 0.0,
            "focalz": 0.0,
            "sprite": 0,
            "scalex": 1.0,
            "scaley": 1.0,
            "scalez": 1.0
        },	
        {
            "x": 0,
            "y": 0,
            "z": -8.5,
            "pitch": 0.0,
            "roll": 0.0,
            "yaw": 0.0,
            "focalx": 4.0,
            "focaly": 0.0,
            "focalz": 3.25,
            "sprite": 1008,
            "scalex": 1.0,
            "scaley": 1.0,
            "scalez": 1.0
        },
        {
            "x": 0.5,
            "y": 0.0,
            "z": -3.5,
            "pitch": 0.0,
            "roll": 0.0,
            "yaw": 0.0,
            "focalx": -4.0,
            "focaly": 0.0,
            "focalz": 2.25,
            "sprite": 1014,
            "scalex": 0.99,
            "scaley": 0.99,
            "scalez": 0.99
        },
        {
            "x": 1.25,
            "y": -2.25,
            "z": -1.0,
            "pitch": -0.36460183660255227,
            "roll": 0.0,
            "yaw": 0.0,
            "focalx": 0.0,
            "focaly": -0.11999999731779099,
            "focalz": 5.0,
            "sprite": 1013,
            "scalex": 1.0,
            "scaley": 1.0,
            "scalez": 1.0
        },
        {
            "x": 1.25,
            "y": 2.25,
            "z": -1.0,
            "pitch": 0.36460183660255227,
            "roll": 0.0,
            "yaw": 0.0,
            "focalx": 0.0,
            "focaly": 0.11999999731779099,
            "focalz": 5.0,
            "sprite": 1011,
            "scalex": 1.0,
            "scaley": 1.0,
            "scalez": 1.0
        },
        {
            "x": 1.0,
            "y": -5.5,
            "z": -4.200000047683716,
            "pitch": -0.3396018366025522,
            "roll": -0.0,
            "yaw": 0.0,
            "focalx": -1.0,
            "focaly": -0.25,
            "focalz": 4.5,
            "sprite": 1012,
            "scalex": 1.0,
            "scaley": 1.0,
            "scalez": 1.0
        },
        {
            "x": 1.0,
            "y": 5.5,
            "z": -4.200000047683716,
            "pitch": -0.38960183660255229,
            "roll": 0.0,
            "yaw": 0.0,
            "focalx": -1.0,
            "focaly": 0.25,
            "focalz": 4.5,
            "sprite": 1010,
            "scalex": 1.0,
            "scaley": 1.0,
            "scalez": 1.0
        },
        {
            "x": 0.0,
            "y": 0.0,
            "z": -8.5,
            "pitch": 0.0,
            "roll": 0.0,
            "yaw": 0.0,
            "focalx": 6.0,
            "focaly": 0.0,
            "focalz": 5.5,
            "sprite": 1009,
            "scalex": 1.0,
            "scaley": 1.0,
            "scalez": 1.0
        }
    ]
}