{
    "version": 1,
    "camera": {
        "ang_degrees": 15,
        "vang_degrees": 10,
        "zoom": 0.1,
        "height": -7,
        "rotate_limit_degrees_min": 0,
        "rotate_limit_degrees_max": 0,
        "rotate_speed": -5
    },
    "limbs": [
        {
            "x": 0,
            "y": 0,
            "z": -1.0,
            "pitch": 0.0,
            "roll": 0.0,
            "yaw": 0.0,
            "focalx": 0.0,
            "focaly": 0.0,
            "focalz": -1.5,
            "sprite": 333,
            "scalex": 0.99,
            "scaley": 0.99,
            "scalez": 0.99
        },
        {
            "x": 0.25,
            "y": 0.0,
            "z": 1.5,
            "pitch": 0.0,
            "roll": 0.0,
            "yaw": 0.0,
            "focalx": 0.0,
            "focaly": 0.0,
            "focalz": 0.0,
            "sprite": 118,
            "scalex": 1.0,
            "scaley": 1.0,
            "scalez": 1.0
        },
        {
            "x": -0.25,
            "y": -1.0,
            "z": 4.0,
            "pitch": -0.7613981633974483,
            "roll": 0.0,
            "yaw": 0.0,
            "focalx": 0.0,
            "focaly": 0.0,
            "focalz": 2.0,
            "sprite": 149,
            "scalex": 1.0,
            "scaley": 1.0,
            "scalez": 1.0
        },
        {
            "x": -0.25,
            "y": 1.0,
            "z": 4.0,
            "pitch": 0.7613981633974483,
            "roll": 0.0,
            "yaw": 0.0,
            "focalx": 0.0,
            "focaly": 0.0,
            "focalz": 2.0,
            "sprite": 151,
            "scalex": 1.0,
            "scaley": 1.0,
            "scalez": 1.0
        },
        {
            "x": 0.20000000000000019,
            "y": -2.5,
            "z": 0.5,
            "pitch": 0.7613981633974483,
            "roll": 0.0,
            "yaw": 0.0,
            "focalx": 0.75,
            "focaly": 0.0,
            "focalz": 0.75,
            "sprite": 123,
            "scalex": 1.0,
            "scaley": 1.0,
            "scalez": 1.0
        },
        {
            "x": 0.20000000000000019,
            "y": 2.5,
            "z": 0.5,
            "pitch": 0.0,
            "roll": 0.0,
            "yaw": 0.0,
            "focalx": 0.75,
            "focaly": 0.0,
            "focalz": 0.75,
            "sprite": 124,
            "scalex": 1.0,
            "scaley": 1.0,
            "scalez": 1.0
        },
        {
            "x": 0.4500000000000002,
            "y": -2.4000000000000005,
            "z": 0.25,
            "pitch": 1.0113981633974483,
            "roll": 0.0,
            "yaw": 0.0,
            "focalx": 1.0,
            "focaly": 0.0,
            "focalz": 1.25,
            "sprite": 19,
            "scalex": 1.0,
            "scaley": 1.0,
            "scalez": 1.0
        },
        {
            "x": 1.4500000000000002,
            "y": 2.25,
            "z": 0.21999999999999998,
            "pitch": 0.0,
            "roll": 0.0,
            "yaw": 0.0,
            "focalx": 2.0,
            "focaly": 0.0,
            "focalz": 3.0,
            "sprite": 914,
            "scalex": 1.05,
            "scaley": 1.0,
            "scalez": 1.0
        },
        {
            "x": 1.0,
            "y": 0.0,
            "z": -1.0,
            "pitch": 0.0,
            "roll": -0.38069908169872415,
            "yaw": 1.5707963267948966,
            "focalx": 0.0,
            "focaly": 0.5,
            "focalz": 3.75,
            "sprite": 31,
            "scalex": 1.01,
            "scaley": 1.01,
            "scalez": 1.01
        },
        {
            "x": 0.0,
            "y": 0.0,
            "z": -1.0,
            "pitch": 0.0,
            "roll": 1.5707963267948966,
            "yaw": 0.0,
            "focalx": 0.25,
            "focaly": -3.5,
            "focalz": 0.5,
            "sprite": 1272,
            "scalex": 1.01,
            "scaley": 1.01,
            "scalez": 1.01
        }
    ]
}