{
	"version": 1,
	"default_attributes": {
		"font_color": {
			"r": 239,
			"g": 237,
			"b": 235,
			"a": 255
		},
		"font_outline_color": {
			"r": 50,
			"g": 29,
			"b": 25,
			"a": 255
		},
		"font_highlight_color": {
			"r": 18,
			"g": 196,
			"b": 131,
			"a": 255
		},
		"font_highlight2_color": {
			"r": 64,
			"g": 192,
			"b": 255,
			"a": 255
		}
	},
	"script_entries": {
		"tutorial5a": {
			"sign": [
				"Porte, mobili e",
				"casse possono bloccarti.",
				"Gli attacchi in mischia",
				"li distruggono come",
				"palle di fuoco, nemici",
				"e massi."
			],
			"attributes": {
				"font": "fonts/pixelmix.ttf#16#2",
				"horizontal_justify": "center",
				"vertical_justify": "center",
				"line_padding": 0,
				"top_padding": 0,
				"inline_img_adjust_x": 0,
				"word_highlights": [],
				"word_highlights2": [
					[],
					[],
					[
						3
					],
					[
						0
					],
					[]
				],
				"video": {
					"background_img": "data/scripts/video_frame_half_noalpha.png",
					"background_border": 8,
					"path": "data/scripts/tutorial5/furniture.ogv",
					"x": 0,
					"y": 0,
					"w": 0,
					"h": 0
				}
			},
			"variables": []
		},
		"tutorial5b": {
			"sign": [
				"Con incantesimi attivi,",
				"libri equipaggiati e",
				"bastoni magici, puoi",
				"accedere a una varieta' di",
				"magie rapidamente.",
				"",
				"$ $ $"
			],
			"attributes": {
				"font": "fonts/pixelmix.ttf#16#2",
				"horizontal_justify": "center",
				"vertical_justify": "center",
				"line_padding": 0,
				"top_padding": 0,
				"inline_img_adjust_x": 0,
				"word_highlights": [],
				"word_highlights2": [
					[
						1,
						2
					],
					[
						0,
						1
					],
					[
						0
					],
					[],
					[
						1
					]
				]
			},
			"variables": [
				{
					"type": "image",
					"value": "*#items/images/SpellbookGreen.png",
					"sizex": 36,
					"sizey": 36
				},
				{
					"type": "image",
					"value": "*#items/images/spells/forcebolt.png",
					"sizex": 0,
					"sizey": 0
				},
				{
					"type": "image",
					"value": "*#items/images/RedMysticStaff.png",
					"sizex": 36,
					"sizey": 36
				}
			]
		},
		"tutorial5c": {
			"sign": [
				"Usa la tua conoscenza della",
				"magia per ripulire questa",
				"stanza dai non morti."
			],
			"attributes": {
				"font": "fonts/pixelmix.ttf#16#2",
				"horizontal_justify": "center",
				"vertical_justify": "center",
				"line_padding": 0,
				"top_padding": 0,
				"inline_img_adjust_x": 0,
				"word_highlights": [],
				"word_highlights2": [
					[],
					[
						2,
						3
					],
					[
						0,
						1,
						2,
						3
					]
				]
			},
			"variables": []
		},
		"tutorial5d": {
			"sign": [
				"Puoi equipaggiare libri",
				"magici difficili usandoli",
				"dalla tua barra.",
				"",
				"Per equipaggiare un libro",
				"dalla tua barra senza",
				"tentare di memorizzarlo,",
				"mantieni $ prima di usare."
			],
			"attributes": {
				"font": "fonts/pixelmix.ttf#16#2",
				"horizontal_justify": "center",
				"vertical_justify": "center",
				"line_padding": 0,
				"top_padding": 0,
				"inline_img_adjust_x": 0,
				"word_highlights": [
					[],
					[
						0,
						1,
						2
					],
					[],
					[
						1
					],
					[],
					[],
					[],
					[],
					[
						0
					]
				],
				"word_highlights2": [
					[],
					[],
					[],
					[],
					[],
					[],
					[
						3
					],
					[
						2
					]
				]
			},
			"variables": [
				{
					"type": "image",
					"value": "*#images/ui/Glyphs/KeyboardGlyphs/Rendered/NamedKeys/Unpressed_Text_Alt_00.png",
					"sizex": 0,
					"sizey": 0
				}
			]
		},
		"tutorial5d_gamepad": {
			"sign": [
				"Puoi equipaggiare libri",
				"difficili, o libri gia'",
				"memorizzati, usandoli",
				"dalla tua barra.",
				"",
				"Alcune magie sono piu'",
				"potenti se lanciate da",
				"un libro equipaggiato."
			],
			"attributes": {
				"font": "fonts/pixelmix.ttf#16#2",
				"horizontal_justify": "center",
				"vertical_justify": "center",
				"line_padding": 0,
				"top_padding": 0,
				"inline_img_adjust_x": 0,
				"word_highlights": [
					[
						2
					],
					[],
					[],
					[
						2
					],
					[
						1,
						2
					]
				],
				"word_highlights2": [
					[],
					[
						0,
						1
					]
				]
			},
			"variables": []
		},
		"tutorial5e": {
			"sign": [
				"Queste pergamene rimuovono",
				"le maledizioni dagli oggetti.",
				"Usale dal tuo",
				"inventario con$ .",
				"$"
			],
			"attributes": {
				"font": "fonts/pixelmix.ttf#16#2",
				"horizontal_justify": "center",
				"vertical_justify": "center",
				"line_padding": 0,
				"top_padding": 0,
				"inline_img_adjust_x": 0,
				"word_highlights": [
					[],
					[],
					[
						0
					],
					[
						0,
						1
					]
				],
				"word_highlights2": [
					[
						2
					],
					[
						0
					]
				]
			},
			"variables": [
				{
					"type": "input_glyph",
					"value": "MenuRightClick"
				},
				{
					"type": "image",
					"value": "*#data/scripts/tutorial5/sign_cursed.png",
					"sizex": 0,
					"sizey": 0
				}
			]
		},
		"tutorial5e_gamepad": {
			"sign": [
				"Queste pergamene rimuovono",
				"le maledizioni dagli oggetti.",
				"Usale dal tuo",
				"inventario con$ .",
				"$"
			],
			"attributes": {
				"font": "fonts/pixelmix.ttf#16#2",
				"horizontal_justify": "center",
				"vertical_justify": "center",
				"line_padding": 0,
				"top_padding": 0,
				"inline_img_adjust_x": 0,
				"word_highlights": [
					[],
					[],
					[
						0
					],
					[
						0,
						1
					]
				],
				"word_highlights2": [
					[
						2
					],
					[
						0
					]
				]
			},
			"variables": [
				{
					"type": "input_glyph",
					"value": "MenuConfirm"
				},
				{
					"type": "image",
					"value": "*#data/scripts/tutorial5/sign_cursed.png",
					"sizex": 0,
					"sizey": 0
				}
			]
		},
		"tutorial5f": {
			"sign": [
				"Bassa Abilita' Magica puo'",
				"far fallire le tue magie.",
				"",
				"$",
				"",
				"Riprova semplicemente!",
				"La pratica rende perfetti."
			],
			"attributes": {
				"font": "fonts/pixelmix.ttf#16#2",
				"font_highlight_color": {
					"r": 255,
					"g": 64,
					"b": 64,
					"a": 255
				},
				"horizontal_justify": "center",
				"vertical_justify": "center",
				"line_padding": 0,
				"top_padding": 0,
				"inline_img_adjust_x": 0,
				"word_highlights": [
					[],
					[
						0
					]
				],
				"word_highlights2": [
					[
						1,
						2
					],
					[
						2
					],
					[],
					[],
					[],
					[
						1,
						2
					]
				],
				"video": {
					"background_img": "data/scripts/video_frame_noalpha.png",
					"background_border": 8,
					"path": "data/scripts/tutorial5/fizzle.ogv",
					"x": 0,
					"y": 0,
					"w": 0,
					"h": 0
				}
			},
			"variables": [
				{
					"type": "image",
					"value": "*#images/ui/SkillSheet/Icons/Casting02_32.png",
					"sizex": 0,
					"sizey": 0
				}
			]
		},
		"tutorial5g": {
			"sign": [
				"Il dungeon nasconde molti",
				"segreti. Alcuni richiedono",
				"abilita' per accedere.",
				"",
				"Spesso, nascondono",
				"grandi ricompense."
			],
			"attributes": {
				"font": "fonts/pixelmix.ttf#16#2",
				"horizontal_justify": "center",
				"vertical_justify": "center",
				"line_padding": 0,
				"top_padding": 0,
				"inline_img_adjust_x": 0,
				"word_highlights": [],
				"word_highlights2": [
					[],
					[
						0,
						2
					],
					[],
					[
						2
					],
					[],
					[
						0,
						1
					]
				]
			},
			"variables": []
		},
		"tutorial5h": {
			"sign": [
				"Libri magici, magie",
				"memorizzate, pergamene e",
				"bastoni magici offrono molti",
				"modi agli incantatori per",
				"sopravvivere e conquistare",
				"il dungeon."
			],
			"attributes": {
				"font": "fonts/pixelmix.ttf#16#2",
				"horizontal_justify": "center",
				"vertical_justify": "center",
				"line_padding": 0,
				"top_padding": 0,
				"inline_img_adjust_x": 0,
				"word_highlights": [],
				"word_highlights2": [
					[],
					[],
					[],
					[
						2
					]
				]
			},
			"variables": []
		},
		"tutorial5i": {
			"sign": [
				"I libri magici ti permettono",
				"di memorizzare incantesimi.",
				"",
				"$",
				"",
				"Usa i libri nel tuo",
				"inventario con$ e [Leggi]",
				"per memorizzare l'incantesimo."
			],
			"attributes": {
				"font": "fonts/pixelmix.ttf#16#2",
				"horizontal_justify": "center",
				"vertical_justify": "center",
				"line_padding": 0,
				"top_padding": 0,
				"inline_img_adjust_x": 0,
				"word_highlights": [
					[],
					[],
					[],
					[],
					[],
					[
						0,
						1
					],
					[
						0,
						1,
						3
					],
					[
						1
					]
				],
				"word_highlights2": [
					[
						0
					],
					[
						1,
						2
					]
				]
			},
			"variables": [
				{
					"type": "image",
					"value": "*#images/ui/SkillSheet/Icons/Magic02_32.png",
					"sizex": 0,
					"sizey": 0
				},
				{
					"type": "input_glyph",
					"value": "MenuRightClick"
				}
			]
		},
		"tutorial5i_gamepad": {
			"sign": [
				"I libri magici ti permettono",
				"di memorizzare incantesimi.",
				"",
				"$",
				"",
				"Usa i libri nel tuo",
				"inventario con$ e [Leggi]",
				"per memorizzare l'incantesimo."
			],
			"attributes": {
				"font": "fonts/pixelmix.ttf#16#2",
				"horizontal_justify": "center",
				"vertical_justify": "center",
				"line_padding": 0,
				"top_padding": 0,
				"inline_img_adjust_x": 0,
				"word_highlights": [
					[],
					[],
					[],
					[],
					[],
					[
						0,
						1
					],
					[
						0,
						1,
						3
					],
					[
						1
					]
				],
				"word_highlights2": [
					[
						0
					],
					[
						1,
						2
					]
				]
			},
			"variables": [
				{
					"type": "image",
					"value": "*#images/ui/SkillSheet/Icons/Magic02_32.png",
					"sizex": 0,
					"sizey": 0
				},
				{
					"type": "input_glyph",
					"value": "MenuConfirm"
				}
			]
		},
		"tutorial5j": {
			"sign": [
				"$",
				"I bastoni magici sono caricati",
				"con un singolo tipo di",
				"magia che ogni avventuriero",
				"puo' usare. Equipaggiali e",
				"lancia da essi con$ ."
			],
			"attributes": {
				"font": "fonts/pixelmix.ttf#16#2",
				"horizontal_justify": "center",
				"vertical_justify": "center",
				"line_padding": 0,
				"top_padding": 0,
				"inline_img_adjust_x": 0,
				"word_highlights": [
					[],
					[],
					[],
					[],
					[],
					[
						0,
						3
					]
				],
				"word_highlights2": [
					[],
					[
						0,
						2
					],
					[],
					[
						2,
						3
					]
				]
			},
			"variables": [
				{
					"type": "image",
					"value": "*#data/scripts/tutorial5/sign_firestaff.png",
					"sizex": 0,
					"sizey": 0
				},
				{
					"type": "input_glyph",
					"value": "Attack"
				}
			]
		},
		"tutorial5k": {
			"sign": [
				"Gli avventurieri devono",
				"capire la magia per",
				"sopravvivere nei",
				"dungeon."
			],
			"attributes": {
				"font": "fonts/pixelmix.ttf#16#2",
				"horizontal_justify": "center",
				"vertical_justify": "center",
				"line_padding": 0,
				"top_padding": 0,
				"inline_img_adjust_x": 0,
				"word_highlights": [],
				"word_highlights2": [
					[],
					[
						1
					]
				]
			},
			"variables": []
		},
		"tutorial5l": {
			"sign": [
				"Alcune magie richiedono",
				"piu' INT e Abilita'",
				"Magica per memorizzare.",
				"",
				"$ $",
				"",
				"Puoi ancora lanciare quelle",
				"magie equipaggiando",
				"il libro."
			],
			"attributes": {
				"font": "fonts/pixelmix.ttf#16#2",
				"horizontal_justify": "center",
				"vertical_justify": "center",
				"line_padding": 0,
				"top_padding": 0,
				"inline_img_adjust_x": 0,
				"word_highlights": [
					[],
					[],
					[],
					[],
					[],
					[],
					[],
					[
						2
					]
				],
				"word_highlights2": [
					[
						2
					],
					[
						1
					],
					[
						2
					],
					[],
					[],
					[],
					[
						3
					]
				]
			},
			"variables": [
				{
					"type": "image",
					"value": "*#images/ui/CharSheet/HUD_CharSheet_INT_00.png",
					"sizex": 0,
					"sizey": 0
				},
				{
					"type": "image",
					"value": "*#images/ui/SkillSheet/Icons/Magic01.png",
					"sizex": 0,
					"sizey": 0
				}
			]
		},
		"tutorial5m": {
			"sign": [
				"Le magie memorizzate appaiono",
				"nella lista magie, e possono",
				"essere messe nella barra.",
				"$",
				"Accedi rapidamente alla",
				"lista con$e prepara",
				"la magia con$ ."
			],
			"attributes": {
				"font": "fonts/pixelmix.ttf#16#2",
				"horizontal_justify": "center",
				"vertical_justify": "center",
				"line_padding": 0,
				"top_padding": 0,
				"inline_img_adjust_x": 0,
				"word_highlights": [
					[],
					[],
					[],
					[],
					[
						1
					],
					[
						1,
						3
					],
					[
						1,
						2
					]
				],
				"word_highlights2": [
					[
						0,
						1
					],
					[
						2,
						3
					],
					[],
					[
						3
					]
				],
				"video": {
					"background_img": "data/scripts/video_frame_noalpha.png",
					"background_border": 8,
					"path": "data/scripts/tutorial5/magiclist_mk.ogv",
					"x": 0,
					"y": 0,
					"w": 0,
					"h": 0
				}
			},
			"variables": [
				{
					"type": "image",
					"value": "*#data/scripts/tutorial5/sign_readyspell.png",
					"sizex": 0,
					"sizey": 0
				},
				{
					"type": "input_glyph",
					"value": "Spell List"
				},
				{
					"type": "input_glyph",
					"value": "MenuRightClick"
				}
			]
		},
		"tutorial5m_gamepad": {
			"sign": [
				"Le magie memorizzate appaiono",
				"nella tua lista magie, e",
				"possono essere messe per uso",
				"rapido nella barra.",
				"$",
				"Accedi alla lista dall'",
				"inventario con$e prepara",
				"la magia con$ ."
			],
			"attributes": {
				"font": "fonts/pixelmix.ttf#16#2",
				"horizontal_justify": "center",
				"vertical_justify": "center",
				"line_padding": 0,
				"top_padding": 0,
				"inline_img_adjust_x": 0,
				"word_highlights": [
					[],
					[],
					[],
					[],
					[],
					[
						2
					],
					[
						1,
						3
					],
					[
						1,
						2
					]
				],
				"word_highlights2": [
					[
						0,
						1
					],
					[
						2,
						3
					],
					[],
					[
						3
					]
				],
				"video": {
					"background_img": "data/scripts/video_frame_noalpha.png",
					"background_border": 8,
					"path": "data/scripts/tutorial5/magiclist_gamepad.ogv",
					"x": 0,
					"y": 0,
					"w": 0,
					"h": 0
				}
			},
			"variables": [
				{
					"type": "image",
					"value": "*#data/scripts/tutorial5/sign_readyspell.png",
					"sizex": 0,
					"sizey": 0
				},
				{
					"type": "input_glyph",
					"value": "MenuPageLeftAlt"
				},
				{
					"type": "input_glyph",
					"value": "MenuConfirm"
				}
			]
		},
		"tutorial5n": {
			"sign": [
				"Lancia la tua magia pronta",
				"con$.",
				"",
				"Lanciare consuma MP,",
				"a seconda della magia."
			],
			"attributes": {
				"font": "fonts/pixelmix.ttf#16#2",
				"horizontal_justify": "center",
				"vertical_justify": "center",
				"line_padding": 0,
				"top_padding": 0,
				"inline_img_adjust_x": 0,
				"word_highlights": [
					[
						0
					],
					[
						1
					]
				],
				"word_highlights2": [
					[
						2
					],
					[],
					[],
					[
						1,
						2
					]
				],
				"video": {
					"background_img": "data/scripts/video_frame_noalpha.png",
					"background_border": 8,
					"path": "data/scripts/tutorial5/cast_memorized.ogv",
					"x": 0,
					"y": 0,
					"w": 0,
					"h": 0
				}
			},
			"variables": [
				{
					"type": "input_glyph",
					"value": "Cast Spell"
				}
			]
		},
		"tutorial5o": {
			"sign": [
				"Premi$ sui libri magici",
				"nel tuo inventario",
				"e seleziona [Impugna] per",
				"equipaggiarli.",
				"",
				"Lancia da libri",
				"impugnati usando$."
			],
			"attributes": {
				"font": "fonts/pixelmix.ttf#16#2",
				"horizontal_justify": "center",
				"vertical_justify": "center",
				"line_padding": 0,
				"top_padding": 0,
				"inline_img_adjust_x": 0,
				"word_highlights": [
					[
						0,
						2
					],
					[],
					[
						1,
						2
					],
					[
						0
					],
					[],
					[
						0,
						2
					],
					[
						1
					]
				],
				"word_highlights2": []
			},
			"variables": [
				{
					"type": "input_glyph",
					"value": "MenuRightClick"
				},
				{
					"type": "input_glyph",
					"value": "Defend"
				}
			]
		},
		"tutorial5o_gamepad": {
			"sign": [
				"Premi$ sui libri magici",
				"nel tuo inventario",
				"e seleziona [Impugna] per",
				"equipaggiarli.",
				"",
				"Lancia da libri",
				"impugnati usando$."
			],
			"attributes": {
				"font": "fonts/pixelmix.ttf#16#2",
				"horizontal_justify": "center",
				"vertical_justify": "center",
				"line_padding": 0,
				"top_padding": 0,
				"inline_img_adjust_x": 0,
				"word_highlights": [
					[
						0,
						2
					],
					[],
					[
						1,
						2
					],
					[
						0
					],
					[],
					[
						0,
						2
					],
					[
						1
					]
				],
				"word_highlights2": []
			},
			"variables": [
				{
					"type": "input_glyph",
					"value": "MenuConfirm"
				},
				{
					"type": "input_glyph",
					"value": "Defend"
				}
			]
		},
		"tutorial5p": {
			"sign": [
				"$",
				"Le pergamene possono",
				"contenere magia speciale",
				"che puo' essere usata",
				"una sola volta."
			],
			"attributes": {
				"font": "fonts/pixelmix.ttf#16#2",
				"horizontal_justify": "center",
				"vertical_justify": "center",
				"line_padding": 0,
				"top_padding": 0,
				"inline_img_adjust_x": 0,
				"word_highlights": [],
				"word_highlights2": [
					[],
					[
						0
					],
					[],
					[
						3
					],
					[
						1
					]
				]
			},
			"variables": [
				{
					"type": "image",
					"value": "*#data/scripts/tutorial4/sign_scroll.png",
					"sizex": 0,
					"sizey": 0
				}
			]
		},
		"tutorial5q": {
			"sign": [
				"Questo cancello puo' solo",
				"essere aperto con una magia",
				"da un libro equipaggiato.",
				"",
				"$ $"
			],
			"attributes": {
				"font": "fonts/pixelmix.ttf#16#2",
				"horizontal_justify": "center",
				"vertical_justify": "center",
				"line_padding": 0,
				"top_padding": 0,
				"inline_img_adjust_x": 0,
				"word_highlights": [],
				"word_highlights2": [
					[
						3
					],
					[],
					[
						2,
						3
					]
				],
				"video": {
					"background_img": "data/scripts/video_frame_noalpha.png",
					"background_border": 8,
					"path": "data/scripts/tutorial5/open_mk.ogv",
					"x": 0,
					"y": 0,
					"w": 0,
					"h": 0
				}
			},
			"variables": [
				{
					"type": "input_glyph",
					"value": "Defend"
				},
				{
					"type": "image",
					"value": "*#items/images/spells/opening.png",
					"sizex": 0,
					"sizey": 0
				}
			]
		},
		"tutorial5q_gamepad": {
			"sign": [
				"Questo cancello puo' solo",
				"essere aperto con una magia",
				"da un libro equipaggiato.",
				"",
				"$ $"
			],
			"attributes": {
				"font": "fonts/pixelmix.ttf#16#2",
				"horizontal_justify": "center",
				"vertical_justify": "center",
				"line_padding": 0,
				"top_padding": 0,
				"inline_img_adjust_x": 0,
				"word_highlights": [],
				"word_highlights2": [
					[
						3
					],
					[],
					[
						2,
						3
					]
				],
				"video": {
					"background_img": "data/scripts/video_frame_noalpha.png",
					"background_border": 8,
					"path": "data/scripts/tutorial5/open_gamepad.ogv",
					"x": 0,
					"y": 0,
					"w": 0,
					"h": 0
				}
			},
			"variables": [
				{
					"type": "input_glyph",
					"value": "Defend"
				},
				{
					"type": "image",
					"value": "*#items/images/spells/opening.png",
					"sizex": 0,
					"sizey": 0
				}
			]
		},
		"tutorial5r": {
			"sign": [
				"Dovrai pensare",
				"rapidamente per ottenere",
				"il massimo dalla",
				"tua magia.",
				"",
				"Assicurati di essere pronto."
			],
			"attributes": {
				"font": "fonts/pixelmix.ttf#16#2",
				"horizontal_justify": "center",
				"vertical_justify": "center",
				"line_padding": 0,
				"top_padding": 0,
				"inline_img_adjust_x": 0,
				"word_highlights": [],
				"word_highlights2": [
					[],
					[
						0,
						1
					]
				]
			},
			"variables": []
		},
		"tutorial5s": {
			"sign": [
				"Attiva questo portale",
				"magico con$ quando sei",
				"pronto la prova finale."
			],
			"attributes": {
				"font": "fonts/pixelmix.ttf#16#2",
				"horizontal_justify": "center",
				"vertical_justify": "center",
				"line_padding": 0,
				"top_padding": 0,
				"inline_img_adjust_x": 0,
				"word_highlights": [
					[
						0
					],
					[
						1
					]
				],
				"word_highlights2": []
			},
			"variables": [
				{
					"type": "input_glyph",
					"value": "Use"
				}
			]
		},
		"tutorial5t": {
			"sign": [
				"I cappelli da mago possono",
				"aumentare la tua INT, che",
				"migliora la tua abilita'magica.",
				"$",
				"Il cappello da mago benedetto",
				"aggiungera' ancora piu' INT."
			],
			"attributes": {
				"font": "fonts/pixelmix.ttf#16#2",
				"horizontal_justify": "center",
				"vertical_justify": "center",
				"line_padding": 0,
				"top_padding": 0,
				"inline_img_adjust_x": 0,
				"word_highlights": [],
				"word_highlights2": [
					[],
					[
						1
					],
					[
						1,
						2
					],
					[],
					[
						1
					],
					[
						4,
						5
					]
				]
			},
			"variables": [
				{
					"type": "image",
					"value": "*#data/scripts/tutorial5/sign_wizardhat.png",
					"sizex": 0,
					"sizey": 0
				}
			]
		},
		"tutorial5u": {
			"sign": [
				"Levitazione",
				"",
				"$ ",
				"",
				"Permette agli avventurieri",
				"di attraversare liquidi",
				"e buche liberamente"
			],
			"attributes": {
				"font": "fonts/pixelmix.ttf#16#2",
				"horizontal_justify": "center",
				"vertical_justify": "center",
				"line_padding": 0,
				"top_padding": 0,
				"inline_img_adjust_x": 0,
				"word_highlights": [],
				"word_highlights2": [
					[],
					[],
					[],
					[],
					[],
					[
						1,
						2
					],
					[
						1,
						2
					]
				]
			},
			"variables": [
				{
					"type": "image",
					"value": "*#items/images/spells/levitation.png",
					"sizex": 0,
					"sizey": 0
				}
			]
		},
		"tutorial5v": {
			"sign": [
				"Pergamena di Ricarica",
				"$ ",
				"I bastoni magici possono",
				"essere ricaricati con",
				"questa pergamena."
			],
			"attributes": {
				"font": "fonts/pixelmix.ttf#16#2",
				"horizontal_justify": "center",
				"vertical_justify": "center",
				"line_padding": 0,
				"top_padding": 0,
				"inline_img_adjust_x": 0,
				"word_highlights": [],
				"word_highlights2": [
					[],
					[],
					[
						0
					],
					[
						1
					],
					[]
				]
			},
			"variables": [
				{
					"type": "image",
					"value": "*#data/scripts/tutorial5/sign_recharge.png",
					"sizex": 0,
					"sizey": 0
				}
			]
		},
		"tutorial5w": {
			"sign": [
				"Le magie sostenute rimangono",
				"attive una volta lanciate, e",
				"continuano a consumare MP.",
				"",
				"$",
				"",
				"Rilancia le magie sostenute",
				"per disattivarle."
			],
			"attributes": {
				"font": "fonts/pixelmix.ttf#16#2",
				"horizontal_justify": "center",
				"vertical_justify": "center",
				"line_padding": 0,
				"top_padding": 0,
				"inline_img_adjust_x": 0,
				"word_highlights": [
					[],
					[],
					[],
					[],
					[],
					[],
					[
						0
					],
					[
						0,
						1
					]
				],
				"word_highlights2": [
					[
						0,
						1
					],
					[
						0
					],
					[
						2,
						3
					]
				],
				"video": {
					"background_img": "data/scripts/video_frame_noalpha.png",
					"background_border": 8,
					"path": "data/scripts/tutorial5/sustained.ogv",
					"x": 0,
					"y": 0,
					"w": 0,
					"h": 0
				}
			},
			"variables": [
				{
					"type": "image",
					"value": "*#items/images/spells/light.png",
					"sizex": 0,
					"sizey": 0
				}
			]
		},
		"tutorial5x": {
			"sign": [
				"Sonno",
				"",
				"$ ",
				"",
				"Fa cadere il bersaglio in",
				"un breve sonno.",
				"I bersagli addormentati si",
				"sveglieranno se feriti."
			],
			"attributes": {
				"font": "fonts/pixelmix.ttf#16#2",
				"horizontal_justify": "center",
				"vertical_justify": "center",
				"line_padding": 0,
				"top_padding": 0,
				"inline_img_adjust_x": 0,
				"word_highlights": [],
				"word_highlights2": [
					[],
					[],
					[],
					[],
					[
						2
					],
					[
						4
					],
					[],
					[
						2
					]
				],
				"video": {
					"background_img": "data/scripts/video_frame_half_noalpha.png",
					"background_border": 8,
					"path": "data/scripts/tutorial5/sleep.ogv",
					"x": 0,
					"y": 0,
					"w": 0,
					"h": 0
				}
			},
			"variables": [
				{
					"type": "image",
					"value": "*#items/images/spells/sleep.png",
					"sizex": 0,
					"sizey": 0
				}
			]
		},
		"tutorial5y": {
			"sign": [
				"$$",
				"Gli MP si rigenerano",
				"col tempo (RGN), o puoi",
				"trovare pozioni di",
				"ripristino magico per",
				"ripristinare subito gli MP."
			],
			"attributes": {
				"font": "fonts/pixelmix.ttf#16#2",
				"horizontal_justify": "center",
				"vertical_justify": "center",
				"line_padding": 0,
				"top_padding": 0,
				"inline_img_adjust_x": 0,
				"word_highlights": [],
				"word_highlights2": [
					[],
					[
						0,
						1
					],
					[
						2
					],
					[],
					[
						0,
						1
					],
					[
						0,
						1,
						2
					]
				]
			},
			"variables": [
				{
					"type": "image",
					"value": "*#data/scripts/tutorial5/sign_restoremp.png",
					"sizex": 0,
					"sizey": 0
				},
				{
					"type": "image",
					"value": "*#images/ui/CharSheet/HUD_CharSheet_REGEN_00.png",
					"sizex": 0,
					"sizey": 0
				}
			]
		},
		"tutorial5z": {
			"sign": [
				"Freddo",
				"",
				"$ ",
				"",
				"Danneggia e",
				"rallenta i bersagli"
			],
			"attributes": {
				"font": "fonts/pixelmix.ttf#16#2",
				"horizontal_justify": "center",
				"vertical_justify": "center",
				"line_padding": 0,
				"top_padding": 0,
				"inline_img_adjust_x": 0,
				"word_highlights": [],
				"word_highlights2": [
					[],
					[],
					[],
					[],
					[
						0
					],
					[
						0
					]
				],
				"video": {
					"background_img": "data/scripts/video_frame_half_noalpha.png",
					"background_border": 8,
					"path": "data/scripts/tutorial5/cold.ogv",
					"x": 0,
					"y": 0,
					"w": 0,
					"h": 0
				}
			},
			"variables": [
				{
					"type": "image",
					"value": "*#items/images/spells/cold.png",
					"sizex": 0,
					"sizey": 0
				}
			]
		}
	}
}